README.rst
jprops2bash.py
setup.py
jprops2bash.egg-info/PKG-INFO
jprops2bash.egg-info/SOURCES.txt
jprops2bash.egg-info/dependency_links.txt
jprops2bash.egg-info/entry_points.txt
jprops2bash.egg-info/not-zip-safe
jprops2bash.egg-info/pbr.json
jprops2bash.egg-info/requires.txt
jprops2bash.egg-info/top_level.txt