Metadata-Version: 1.0
Name: jprops2bash
Version: 0.0.2
Summary: Convert Java properties file to bash env var script
Home-page: https://github.com/msabramo/jprops2bash
Author: Marc Abramowitz
Author-email: msabramo@gmail.com
License: MIT
Keywords: java properties
Platform: UNKNOWN
